cat9kthousandeyesctl/__init__.py
cat9kthousandeyesctl/main.py
cat9kthousandeyesctl/thousandeyes/__init__.py
cat9kthousandeyesctl/thousandeyes/configs.py
cat9kthousandeyesctl/thousandeyes/deploy.py
cat9kthousandeyesctl/thousandeyes/netconf.py
cat9kthousandeyesctl/thousandeyes/progressbar.py
cat9kthousandeyesctl/thousandeyes/status.py
cat9kthousandeyesctl/thousandeyes/undeploy.py
cat9kthousandeyesctl/thousandeyes/verify.py
cat9kthousandeyesctl-0.0.2.dist-info/LICENSE
cat9kthousandeyesctl-0.0.2.dist-info/METADATA
cat9kthousandeyesctl-0.0.2.dist-info/WHEEL
cat9kthousandeyesctl-0.0.2.dist-info/entry_points.txt
cat9kthousandeyesctl-0.0.2.dist-info/top_level.txt
cat9kthousandeyesctl-0.0.2.dist-info/RECORD
