Metadata-Version: 2.1
Name: cat9kthousandeyesctl
Version: 0.0.2
Summary: Cisco Catalyst 9000 with Thousand Eyes agents
Home-page: https://github.com/robertcsapo/cat9kthousandeyesctl
Author: Robert Csapo
Author-email: rcsapo@cisco.com
License: CISCO SAMPLE CODE LICENSE
Platform: UNKNOWN
Classifier: Programming Language :: Python :: 3.7
Classifier: Operating System :: OS Independent
Classifier: Topic :: Software Development :: Build Tools
Classifier: License :: Other/Proprietary License
Requires-Python: >=3.7
Requires-Dist: click (==7.1.2)
Requires-Dist: PyYAML (==5.4.1)
Requires-Dist: ncclient (==0.6.10)
Requires-Dist: xmltodict (==0.12.0)
Requires-Dist: rich (==10.1.0)
